{"v":5,"entries":{"passwordchecker--default":{"type":"story","id":"passwordchecker--default","name":"Default","title":"PasswordChecker","importPath":"./src/stories/PasswordChecker.stories.tsx","componentPath":"./src/index.tsx","tags":["dev","test"]},"passwordchecker--with-custom-class-name":{"type":"story","id":"passwordchecker--with-custom-class-name","name":"With Custom Class Name","title":"PasswordChecker","importPath":"./src/stories/PasswordChecker.stories.tsx","componentPath":"./src/index.tsx","tags":["dev","test"]},"passwordchecker--in-small-container":{"type":"story","id":"passwordchecker--in-small-container","name":"In Small Container","title":"PasswordChecker","importPath":"./src/stories/PasswordChecker.stories.tsx","componentPath":"./src/index.tsx","tags":["dev","test"]},"passwordchecker--custom-icon-and-colors":{"type":"story","id":"passwordchecker--custom-icon-and-colors","name":"Custom Icon And Colors","title":"PasswordChecker","importPath":"./src/stories/PasswordChecker.stories.tsx","componentPath":"./src/index.tsx","tags":["dev","test"]},"passwordchecker--custom-messages":{"type":"story","id":"passwordchecker--custom-messages","name":"Custom Messages","title":"PasswordChecker","importPath":"./src/stories/PasswordChecker.stories.tsx","componentPath":"./src/index.tsx","tags":["dev","test"]},"passwordchecker--custom-messages-rtl":{"type":"story","id":"passwordchecker--custom-messages-rtl","name":"Custom Messages RTL","title":"PasswordChecker","importPath":"./src/stories/PasswordChecker.stories.tsx","componentPath":"./src/index.tsx","tags":["dev","test"]}}}
